{"cameraMode":{"drawMode":0,"name":"Shaded","section":"Shading Mode"},"sceneLighting":true,"audioPlay":false,"sceneViewState":{"m_AlwaysRefresh":false,"showFog":true,"showSkybox":true,"showFlares":true,"showImageEffects":true,"showParticleSystems":true,"showVisualEffectGraphs":true,"m_FxEnabled":true},"in2DMode":false,"pivot":{"x":-3.553629159927368,"y":6.78972864151001,"z":-5.2986860275268559},"rotation":{"x":-0.42112985253334048,"y":-0.35751810669898989,"z":0.18501853942871095,"w":-0.8129544854164124},"size":0.8660253882408142,"orthographic":false}